pycuc/__init__.py
pycuc/app.py
pycuc/config/__init__.py
pycuc/config/setting.py
pycuc/docs/__init__.py
pycuc/docs/cuc.py
Python_Custom_Unit_Converter-1.0.0.dist-info/LICENSE
Python_Custom_Unit_Converter-1.0.0.dist-info/METADATA
Python_Custom_Unit_Converter-1.0.0.dist-info/WHEEL
Python_Custom_Unit_Converter-1.0.0.dist-info/top_level.txt
Python_Custom_Unit_Converter-1.0.0.dist-info/RECORD
