Metadata-Version: 2.1
Name: Python-Custom-Unit-Converter
Version: 1.0.0
Summary: PyCUC: A lightweight Python package for creating custom unit conversions.
Author: Sina Gilassi
Author-email: <sina.gilassi@gmail.com>
License: MIT
Keywords: python,chemical engineering,custom unit conversion,PyCUC
Classifier: Development Status :: 1 - Planning
Classifier: Intended Audience :: Education
Classifier: Programming Language :: Python :: 3
Classifier: Operating System :: Unix
Classifier: Operating System :: MacOS :: MacOS X
Classifier: Operating System :: Microsoft :: Windows
Requires-Python: >=3.6
License-File: LICENSE
Requires-Dist: pandas
Requires-Dist: numpy
